docs/source/conf.py
docs/source/examples/__init__.py
docs/source/examples/autosweep.py
docs/source/examples/beam.py
docs/source/examples/boundschecking.py
docs/source/examples/breakdowns.py
docs/source/examples/checking_result_changes.py
docs/source/examples/debug.py
docs/source/examples/docstringparsing.py
docs/source/examples/evaluated_fixed_variables.py
docs/source/examples/evaluated_free_variables.py
docs/source/examples/external_constraint.py
docs/source/examples/external_function.py
docs/source/examples/external_sp.py
docs/source/examples/freeing_fixed_variables.py
docs/source/examples/gettingstarted.py
docs/source/examples/issue_1513.py
docs/source/examples/issue_1522.py
docs/source/examples/loose_constraintsets.py
docs/source/examples/migp.py
docs/source/examples/model_var_access.py
docs/source/examples/performance_modeling.py
docs/source/examples/plot_sweep1d.py
docs/source/examples/primal_infeasible_ex1.py
docs/source/examples/primal_infeasible_ex2.py
docs/source/examples/relaxation.py
docs/source/examples/simple_box.py
docs/source/examples/simple_sp.py
docs/source/examples/simpleflight.py
docs/source/examples/sin_approx_example.py
docs/source/examples/sp_to_gp_sweep.py
docs/source/examples/sub_multi_values.py
docs/source/examples/substitutions.py
docs/source/examples/tight_constraintsets.py
docs/source/examples/treemap.py
docs/source/examples/unbounded.py
docs/source/examples/vectorization.py
docs/source/examples/vectorize.py
docs/source/examples/water_tank.py
docs/source/examples/x_greaterthan_1.py
docs/source/examples/breakdowns/solartest.py
docs/source/figures/solartest.py
gpkit/__init__.py
gpkit/breakdowns.py
gpkit/build.py
gpkit/exceptions.py
gpkit/globals.py
gpkit/model.py
gpkit/printing.py
gpkit/solutions.py
gpkit/units.py
gpkit/varkey.py
gpkit/varmap.py
gpkit/constraints/__init__.py
gpkit/constraints/array.py
gpkit/constraints/bounded.py
gpkit/constraints/costed.py
gpkit/constraints/loose.py
gpkit/constraints/relax.py
gpkit/constraints/set.py
gpkit_core-0.1.6.dist-info/licenses/LICENSE
gpkit_core-0.1.6.dist-info/METADATA
gpkit_core-0.1.6.dist-info/WHEEL
gpkit_core-0.1.6.dist-info/top_level.txt
gpkit_core-0.1.6.dist-info/RECORD
