Metadata-Version: 2.4
Name: gpkit-core
Version: 0.1.6
Summary: Package for defining and manipulating geometric programming models.
Author-email: Warren Hoburg <whoburg@alum.mit.edu>
License: The MIT License (MIT)
Project-URL: Homepage, https://www.github.com/beautifulmachines/gpkit-core
Classifier: Programming Language :: Python :: 3
Classifier: License :: OSI Approved :: MIT License
Classifier: Operating System :: OS Independent
Requires-Python: >=3.8
License-File: LICENSE
Requires-Dist: numpy>=1.16.4
Requires-Dist: pint>=0.8.1
Requires-Dist: plotly>=5.3.0
Requires-Dist: scipy>=1.7.0
Requires-Dist: adce>=1.3.2
Requires-Dist: cvxopt>=1.1.8
Requires-Dist: matplotlib>=3.3.0
Provides-Extra: lint
Requires-Dist: isort>=5.12.0; extra == "lint"
Requires-Dist: black>=24.1.0; extra == "lint"
Requires-Dist: flake8>=7.0.0; extra == "lint"
Requires-Dist: pylint>=4.0.0; extra == "lint"
Requires-Dist: import-linter>=2.3; extra == "lint"
Provides-Extra: test
Requires-Dist: pytest>=8.0.0; extra == "test"
Dynamic: license-file
